ritech/__init__.py
ritech/google_transit/agency.txt
ritech/google_transit/calendar.txt
ritech/google_transit/feed_info.txt
ritech/google_transit/routes.txt
ritech/google_transit/shapes.txt
ritech/google_transit/stop_times.txt
ritech/google_transit/stops.txt
ritech/google_transit/trips.txt
ritech/proto/__init__.py
ritech/proto/compile.sh
ritech/proto/gtfs-realtime.proto
ritech/proto/gtfs_realtime_pb2.py
ritech/proto/gtfs_realtime_pb2.pyi
ritech/transit/__init__.py
ritech/transit/realtime.py
ritech-0.0.1.dist-info/METADATA
ritech-0.0.1.dist-info/WHEEL
ritech-0.0.1.dist-info/RECORD
